README.md
setup.py
bin/freenome-build
freenome_build/VERSION
freenome_build/__init__.py
freenome_build/db.py
freenome_build/deploy.py
freenome_build/develop.py
freenome_build/github.py
freenome_build/manage-pipeline-data.py
freenome_build/util.py
freenome_build/version_utils.py
freenome_build.egg-info/PKG-INFO
freenome_build.egg-info/SOURCES.txt
freenome_build.egg-info/dependency_links.txt
freenome_build.egg-info/requires.txt
freenome_build.egg-info/top_level.txt
freenome_build/database_template/Dockerfile
freenome_build/database_template/Makefile
freenome_build/database_template/README.md
freenome_build/database_template/docker-entrypoint-initdb.d/devssl.sh
freenome_build/database_template/scripts/drop
freenome_build/database_template/scripts/example_insert_test_data.sh
freenome_build/database_template/scripts/example_insert_test_data.sql
freenome_build/database_template/scripts/migrate
freenome_build/database_template/scripts/setup
freenome_build/database_template/scripts/setup.sql