Metadata-Version: 1.0
Name: freenome-build
Version: 1.0.13
Summary: Freenome build
Home-page: https://github.com/freenome/freenome-build
Author: Nathan Boley
Author-email: nathan.boley@freenome.com
License: UNKNOWN
Platform: UNKNOWN
